{
    "data": {
        "currentTime": null,
        "temperature": null,
        "humidity": null,
        "isScheduleMode": 0,
        "batLevel": 0,
        "changedtime": [
            {
                "internettime": 1,
                "Ttime": "02:02",
                "Tdate": "01/01/2021",
                "min": 0,
                "hour": 0,
                "day": 0,
                "month": 0,
                "year": 0
            }
        ]
    },
    "relays": [
        {
            "name": "Fruit",
            "pinnumber": 27,
            "pin": "27",
            "isRunning": 1,
            "isEnabled": 0,
            "active": 1,
            "times": [
                {
                    "startTime": "12:30",
                    "duration": 30,
                    "hour": 12,
                    "min": 30
                }
            ]
        },
        {
            "name": "Vegetable",
            "pinnumber": 26,
            "pin": "26",
            "isRunning": 1,
            "isEnabled": 0,
            "active": 1,
            "times": [
                {
                    "startTime": "13:00",
                    "duration": 30,
                    "hour": 13,
                    "min": 0
                }
            ]
        },
        {
            "name": "Cypress",
            "pinnumber": 25,
            "pin": "25",
            "isRunning": 1,
            "isEnabled": 0,
            "active": 1,
            "times": [
                {
                    "startTime": "15:40",
                    "duration": 30,
                    "hour": 15,
                    "min": 40
                }
            ]
        }
    ]
}